sqlitehouse.py
sqlitehouse-1.2.dist-info/DESCRIPTION.rst
sqlitehouse-1.2.dist-info/METADATA
sqlitehouse-1.2.dist-info/RECORD
sqlitehouse-1.2.dist-info/WHEEL
sqlitehouse-1.2.dist-info/metadata.json
sqlitehouse-1.2.dist-info/top_level.txt
